cvd/.uuid
cvd/datasets/__init__.py
cvd/datasets/annotations/__init__.py
cvd/datasets/annotations/coco.py
cvd/datasets/annotations/image_annotation.py
cvd/datasets/annotations/importer/__init__.py
cvd/datasets/annotations/importer/images/__init__.py
cvd/datasets/annotations/importer/images/cvat.py
cvd/datasets/annotations/importer/images/toloka.py
cvd/datasets/annotations/importer/video/__init__.py
cvd/datasets/annotations/importer/video/cvat.py
cvd/datasets/annotations/objects.py
cvd/datasets/annotations/polygon.py
cvd/datasets/annotations/rbbox.py
cvd/datasets/annotations/sbbox.py
cvd/datasets/annotations/type.py
cvd/datasets/annotations/video_annotation.py
cvd/datasets/augumentation/__init__.py
cvd/datasets/augumentation/crop.py
cvd/datasets/augumentation/filters.py
cvd/datasets/augumentation/flip.py
cvd/datasets/augumentation/rotate.py
cvd/datasets/augumentation/utils.py
cvd/datasets/autoannotation/__init__.py
cvd/datasets/autoannotation/iautoannotator.py
cvd/datasets/autoannotation/retinafaceannotator.py
cvd/datasets/autoannotation/topbodyannotator.py
cvd/datasets/common.py
cvd/datasets/converters.py
cvd/datasets/exporter/__init__.py
cvd/datasets/exporter/xml.py
cvd/datasets/filters.py
cvd/datasets/image_dataset.py
cvd/datasets/image_dataset_item.py
cvd/datasets/importer/__init__.py
cvd/datasets/importer/cocoimages.py
cvd/datasets/importer/rawimages.py
cvd/datasets/importer/rawvideo.py
cvd/datasets/interfaces/__init__.py
cvd/datasets/interfaces/iannotation.py
cvd/datasets/interfaces/idataset.py
cvd/datasets/interfaces/interface.py
cvd/datasets/merge.py
cvd/datasets/meta.py
cvd/datasets/samplers.py
cvd/datasets/selection.py
cvd/datasets/torchdataset.py
cvd/datasets/transformations/__init__.py
cvd/datasets/transformations/normalize.py
cvd/datasets/transformations/resize.py
cvd/datasets/transformers.py
cvd/datasets/video_dataset.py
cvd/datasets/video_dataset_item.py
cvd/datasets/zoo/__init__.py
cvd/datasets/zoo/datasets.py
cvd-0.1.7.dist-info/METADATA
cvd-0.1.7.dist-info/WHEEL
cvd-0.1.7.dist-info/RECORD
