Metadata-Version: 2.1
Name: cvd
Version: 0.1.7
Summary: 
Author: bogoslovskiy_nn
Author-email: bogoslovskiy_nn@bw-sw.com
Requires-Python: >=3.8,<4.0
Classifier: Programming Language :: Python :: 3
Classifier: Programming Language :: Python :: 3.8
Classifier: Programming Language :: Python :: 3.9
Classifier: Programming Language :: Python :: 3.10
Classifier: Programming Language :: Python :: 3.11
Requires-Dist: albumentations (>=1.3.0,<2.0.0)
Requires-Dist: beartype (>=0.17.2,<0.18.0)
Requires-Dist: beautifulsoup4 (>=4.12.3,<5.0.0)
Requires-Dist: boto3 (>=1.26.26,<2.0.0)
Requires-Dist: boto3-type-annotations (>=0.3.1,<0.4.0)
Requires-Dist: botocore (>=1.29.26,<2.0.0)
Requires-Dist: dataclasses-json (>=0.6.4,<0.7.0)
Requires-Dist: imagesize (>=1.4.1,<2.0.0)
Requires-Dist: ipython (==8.8.0)
Requires-Dist: lxml (>=4.9.1,<5.0.0)
Requires-Dist: matplotlib (>=3.6.2,<4.0.0)
Requires-Dist: pandas (==2.0.0)
Requires-Dist: tqdm (>=4.64.1,<5.0.0)
